martincesar/__init__.py
martincesar/operaciones.py
MartinCesar-0.1.3.dist-info/LICENSE
MartinCesar-0.1.3.dist-info/METADATA
MartinCesar-0.1.3.dist-info/WHEEL
MartinCesar-0.1.3.dist-info/top_level.txt
MartinCesar-0.1.3.dist-info/RECORD
