Metadata-Version: 2.1
Name: MartinCesar
Version: 0.1.3
Summary: Descripción de lo que hace tu librería
Author: Martin
Author-email: tu.email@example.com
Requires-Python: >=3.6
License-File: LICENSE
